{"created_at":"Sun Jan 27 06:41:22 +0000 2019","id":1089413035431809024,"id_str":"1089413035431809024","text":"When in times of #metoo, people abuse this movement to get money. #MichaelJackson is innocent! #StopLeavingNeveland #Followthemoney","source":"\u003ca href=\"http:\/\/twitter.com\" rel=\"nofollow\"\u003eTwitter Web Client\u003c\/a\u003e","truncated":false,"in_reply_to_status_id":null,"in_reply_to_status_id_str":null,"in_reply_to_user_id":null,"in_reply_to_user_id_str":null,"in_reply_to_screen_name":null,"user":{"id":617298392,"id_str":"617298392","name":"she\u2764\ufe0fmichaeljackson","screen_name":"amelieamale","location":null,"url":null,"description":"neverland","translator_type":"none","protected":false,"verified":false,"followers_count":111,"friends_count":294,"listed_count":1,"favourites_count":1243,"statuses_count":727,"created_at":"Sun Jun 24 17:16:08 +0000 2012","utc_offset":null,"time_zone":null,"geo_enabled":false,"lang":"en","contributors_enabled":false,"is_translator":false,"profile_background_color":"C0DEED","profile_background_image_url":"http:\/\/abs.twimg.com\/images\/themes\/theme1\/bg.png","profile_background_image_url_https":"https:\/\/abs.twimg.com\/images\/themes\/theme1\/bg.png","profile_background_tile":false,"profile_link_color":"1DA1F2","profile_sidebar_border_color":"C0DEED","profile_sidebar_fill_color":"DDEEF6","profile_text_color":"333333","profile_use_background_image":true,"profile_image_url":"http:\/\/pbs.twimg.com\/profile_images\/719875653290602496\/jGuf4-aX_normal.jpg","profile_image_url_https":"https:\/\/pbs.twimg.com\/profile_images\/719875653290602496\/jGuf4-aX_normal.jpg","profile_banner_url":"https:\/\/pbs.twimg.com\/profile_banners\/617298392\/1435859539","default_profile":true,"default_profile_image":false,"following":null,"follow_request_sent":null,"notifications":null},"geo":null,"coordinates":null,"place":null,"contributors":null,"is_quote_status":false,"quote_count":0,"reply_count":0,"retweet_count":0,"favorite_count":0,"entities":{"hashtags":[{"text":"metoo","indices":[17,23]},{"text":"MichaelJackson","indices":[66,81]},{"text":"StopLeavingNeveland","indices":[95,115]},{"text":"Followthemoney","indices":[116,131]}],"urls":[],"user_mentions":[],"symbols":[]},"favorited":false,"retweeted":false,"filter_level":"low","lang":"en","timestamp_ms":"1548571282619"}
{"created_at":"Sun Jan 27 06:41:26 +0000 2019","id":1089413051906838533,"id_str":"1089413051906838533","text":"RT @skd7: \u3053\u306e\u671d\u65e5\u65b0\u805e\u306e\u8a18\u8005\u306f\u4f0a\u85e4\u548c\u5b50\u542b\u3081\u3066\u3001\u6839\u62e0\u306e\u306a\u3044\u30c7\u30de\u3084\u5dee\u5225\u306e\u652f\u63f4\u8005\u3060\u304b\u3089\u3069\u3046\u3057\u3088\u3046\u3082\u306a\u3044\u306a\u3002 #MeToo \u304c\u65e5\u672c\u3067\u5e83\u304c\u3089\u306a\u3044\u7406\u7531\u3068\u3057\u3066\u3001\u3053\u3046\u3044\u3063\u305f\u30c0\u30e1\u306a\u8a18\u8005\u306e\u305b\u3044\u3002\u3061\u3083\u3093\u3068\u6d3b\u52d5\u3057\u3066\u3044\u308b\u4eba\u3092\u53d6\u308a\u4e0a\u3052\u305a\u3001\u5b89\u6613\u306b\u3059\u3050\u30a2\u30af\u30bb\u30b9\u3067\u304d\u308b\u4eba\u3092\u4f7f\u3046\u3053\u3068\u3067\u9593\u9055\u3046\u3002 https\u2026","source":"\u003ca href=\"http:\/\/twitter.com\/download\/android\" rel=\"nofollow\"\u003eTwitter for Android\u003c\/a\u003e","truncated":false,"in_reply_to_status_id":null,"in_reply_to_status_id_str":null,"in_reply_to_user_id":null,"in_reply_to_user_id_str":null,"in_reply_to_screen_name":null,"user":{"id":95057615,"id_str":"95057615","name":"\u4e80\u6238\u592a\u90ce","screen_name":"yottssi","location":null,"url":null,"description":"( ;\u2200;)\u4ed6\u79f0\u3000\u6c17\u6301\u3061\u60aa\u3044\u5de6\u7ffc(\u3064\u0434`)\u4e14\u3064\u3001\n\u6e05\u7fa9\u660e\u8a8d\u5b9a\u30cd\u30c8\u30a6\u30e8( ;\u2200;)","translator_type":"none","protected":false,"verified":false,"followers_count":68,"friends_count":72,"listed_count":65,"favourites_count":7383,"statuses_count":11890,"created_at":"Sun Dec 06 19:33:28 +0000 2009","utc_offset":null,"time_zone":null,"geo_enabled":false,"lang":"ja","contributors_enabled":false,"is_translator":false,"profile_background_color":"C0DEED","profile_background_image_url":"http:\/\/abs.twimg.com\/images\/themes\/theme1\/bg.png","profile_background_image_url_https":"https:\/\/abs.twimg.com\/images\/themes\/theme1\/bg.png","profile_background_tile":false,"profile_link_color":"0084B4","profile_sidebar_border_color":"FFFFFF","profile_sidebar_fill_color":"DDEEF6","profile_text_color":"333333","profile_use_background_image":true,"profile_image_url":"http:\/\/pbs.twimg.com\/profile_images\/562036126\/wp01_1024_normal.jpg","profile_image_url_https":"https:\/\/pbs.twimg.com\/profile_images\/562036126\/wp01_1024_normal.jpg","profile_banner_url":"https:\/\/pbs.twimg.com\/profile_banners\/95057615\/1398850127","default_profile":false,"default_profile_image":false,"following":null,"follow_request_sent":null,"notifications":null},"geo":null,"coordinates":null,"place":null,"contributors":null,"retweeted_status":{"created_at":"Sun Jan 27 02:20:24 +0000 2019","id":1089347362076512256,"id_str":"1089347362076512256","text":"\u3053\u306e\u671d\u65e5\u65b0\u805e\u306e\u8a18\u8005\u306f\u4f0a\u85e4\u548c\u5b50\u542b\u3081\u3066\u3001\u6839\u62e0\u306e\u306a\u3044\u30c7\u30de\u3084\u5dee\u5225\u306e\u652f\u63f4\u8005\u3060\u304b\u3089\u3069\u3046\u3057\u3088\u3046\u3082\u306a\u3044\u306a\u3002 #MeToo \u304c\u65e5\u672c\u3067\u5e83\u304c\u3089\u306a\u3044\u7406\u7531\u3068\u3057\u3066\u3001\u3053\u3046\u3044\u3063\u305f\u30c0\u30e1\u306a\u8a18\u8005\u306e\u305b\u3044\u3002\u3061\u3083\u3093\u3068\u6d3b\u52d5\u3057\u3066\u3044\u308b\u4eba\u3092\u53d6\u308a\u4e0a\u3052\u305a\u3001\u5b89\u6613\u306b\u3059\u3050\u30a2\u30af\u30bb\u30b9\u3067\u304d\u308b\u4eba\u3092\u4f7f\u2026 https:\/\/t.co\/20LjP3Z6K3","display_text_range":[0,140],"source":"\u003ca href=\"http:\/\/twitter.com\/download\/iphone\" rel=\"nofollow\"\u003eTwitter for iPhone\u003c\/a\u003e","truncated":true,"in_reply_to_status_id":null,"in_reply_to_status_id_str":null,"in_reply_to_user_id":null,"in_reply_to_user_id_str":null,"in_reply_to_screen_name":null,"user":{"id":40851097,"id_str":"40851097","name":"\u3084\u3093","screen_name":"skd7","location":"\u5343\u4ee3\u7530\u533a\u5916\u795e\u75307\u4e01\u76ee(\u73fe\u5b9f\u3067\u306f\u5916\u795e\u7530\u306f6\u4e01\u76ee\u307e\u3067)","url":"http:\/\/www.skd7.com\/","description":"\u4e3b\u306b\u30e1\u30a4\u30c9\u55ab\u8336\uff08\u30b3\u30b9\u30d7\u30ec\u30ab\u30d5\u30a7&\u30b3\u30f3\u30ab\u30d5\u30a7\uff09\u3068\u79cb\u8449\u539f\u3068\u30aa\u30bf\u30af\u305d\u306e\u5468\u8fba\u6587\u5316\u30023\u30ad\u30e3\u30ea\u30a2\u516c\u5f0f\u3067\u79cb\u8449\u539f\u306e\u60c5\u5831\u30b5\u30a4\u30c8\u3092\u4f01\u753b\u904b\u55b6\u3057\u3066\u307e\u3057\u305f\u3002\u305d\u306e\u524d\u306f\u67d0\u7af6\u99ac\u30e1\u30c7\u30a3\u30a2\u306e\u526f\u7de8\u96c6\u9577\u3068\u304b\u3002\u30a6\u30a7\u30d6\u3084\u5317\u6d77\u9053\u3001\u56f3\u66f8\u9928\u3001\u672c\u5c4b\u30cd\u30bf\u3082\u3042\u308a\u3002\u300c\u30e1\u30a4\u30c9\u30ab\u30d5\u30a7\u6279\u8a55\u300d\u3067\u306f\u5dfb\u982d\u300c\u30e1\u30a4\u30c9\u55ab\u8336\u3001\u306f\u3058\u3081\u3066\u306e\u9078\u3073\u65b9\u30fc\u30fc\u30e1\u30a4\u30c9\u55ab\u8336\u30dd\u30b8\u30b7\u30e7\u30cb\u30f3\u30b0\u30de\u30c3\u30d7\u300d\u3092\u62c5\u5f53\u3002\u9053\u7523\u5b50\u3002","translator_type":"none","protected":false,"verified":false,"followers_count":25284,"friends_count":9211,"listed_count":895,"favourites_count":1545,"statuses_count":102668,"created_at":"Mon May 18 10:46:57 +0000 2009","utc_offset":null,"time_zone":null,"geo_enabled":false,"lang":"ja","contributors_enabled":false,"is_translator":false,"profile_background_color":"0099B9","profile_background_image_url":"http:\/\/abs.twimg.com\/images\/themes\/theme4\/bg.gif","profile_background_image_url_https":"https:\/\/abs.twimg.com\/images\/themes\/theme4\/bg.gif","profile_background_tile":false,"profile_link_color":"0099B9","profile_sidebar_border_color":"5ED4DC","profile_sidebar_fill_color":"95E8EC","profile_text_color":"3C3940","profile_use_background_image":true,"profile_image_url":"http:\/\/pbs.twimg.com\/profile_images\/378800000804628824\/61c39816217bc3b0d90696bd74737763_normal.jpeg","profile_image_url_https":"https:\/\/pbs.twimg.com\/profile_images\/378800000804628824\/61c39816217bc3b0d90696bd74737763_normal.jpeg","profile_banner_url":"https:\/\/pbs.twimg.com\/profile_banners\/40851097\/1449480284","default_profile":false,"default_profile_image":false,"following":null,"follow_request_sent":null,"notifications":null},"geo":null,"coordinates":null,"place":null,"contributors":null,"quoted_status_id":1088995851316293632,"quoted_status_id_str":"1088995851316293632","quoted_status":{"created_at":"Sat Jan 26 03:03:38 +0000 2019","id":1088995851316293632,"id_str":"1088995851316293632","text":"\u56f0\u96e3\u3092\u62b1\u3048\u308b\u5c11\u5973\u305f\u3061\u306b\u5bc4\u308a\u6dfb\u3046\u4ec1\u85e4\u5922\u4e43\u3055\u3093\u306e\u3053\u3068\u3092\u66f8\u304d\u307e\u3057\u305f\u2192\uff08\u30d5\u30ed\u30f3\u30c8\u30e9\u30f3\u30ca\u30fc\uff09\u4e00\u822c\u793e\u56e3\u6cd5\u4eba\u300c\uff23\uff4f\uff4c\uff41\uff42\uff4f\u300d\u4ee3\u8868\u30fb\u4ec1\u85e4\u5922\u4e43\u3055\u3093\u3000\u73fe\u4ee3\u3092\u3055\u307e\u3088\u3046\u5c11\u5973\u305f\u3061\u3068\uff1a\u671d\u65e5\u65b0\u805e\u30c7\u30b8\u30bf\u30eb https:\/\/t.co\/Glb9nJbFpI","source":"\u003ca href=\"http:\/\/twitter.com\" rel=\"nofollow\"\u003eTwitter Web Client\u003c\/a\u003e","truncated":false,"in_reply_to_status_id":null,"in_reply_to_status_id_str":null,"in_reply_to_user_id":null,"in_reply_to_user_id_str":null,"in_reply_to_screen_name":null,"user":{"id":1612281888,"id_str":"1612281888","name":"\u5927\u4e45\u4fdd\u771f\u7d00","screen_name":"maki_okubo","location":null,"url":"http:\/\/www.asahi.com\/","description":"\u671d\u65e5\u65b0\u805e\u7de8\u96c6\u59d4\u54e1\u3002\uff11\uff19\uff18\uff17\u5e74\u304b\u3089\u8a18\u8005\u3092\u3057\u3066\u3044\u307e\u3059\u3002\u304a\u3082\u306b\u793e\u4f1a\u90e8\u7551\u3092\u6b69\u3044\u3066\u304d\u307e\u3057\u305f\u3002\u5e02\u4e95\u306e\u4eba\u3005\u306e\u55b6\u307f\u3001\u3075\u3064\u3046\u306e\u4eba\u305f\u3061\u306e\u3053\u3068\u3092\u66f8\u304d\u305f\u3044\u3068\u601d\u3063\u3066\u304d\u307e\u3057\u305f\u3002\u6c34\u306e\u4e2d\u306f\u5f97\u610f\u3067\u3059\u3002\u6295\u7a3f\u5185\u5bb9\u306f\u671d\u65e5\u65b0\u805e\u3092\u4ee3\u8868\u3059\u308b\u3082\u306e\u3067\u306f\u306a\u304f\u3001\u30ea\u30f3\u30af\u3084\uff32\uff34\u306f\u5fc5\u305a\u3057\u3082\u5185\u5bb9\u306b\u8cdb\u610f\u3092\u793a\u3059\u3082\u306e\u3067\u306f\u3042\u308a\u307e\u305b\u3093\u3002\u3054\u4e86\u627f\u304f\u3060\u3055\u3044\u3002","translator_type":"none","protected":false,"verified":true,"followers_count":3547,"friends_count":275,"listed_count":122,"favourites_count":168,"statuses_count":990,"created_at":"Mon Jul 22 08:02:32 +0000 2013","utc_offset":null,"time_zone":null,"geo_enabled":false,"lang":"ja","contributors_enabled":false,"is_translator":false,"profile_background_color":"C0DEED","profile_background_image_url":"http:\/\/abs.twimg.com\/images\/themes\/theme1\/bg.png","profile_background_image_url_https":"https:\/\/abs.twimg.com\/images\/themes\/theme1\/bg.png","profile_background_tile":false,"profile_link_color":"1DA1F2","profile_sidebar_border_color":"C0DEED","profile_sidebar_fill_color":"DDEEF6","profile_text_color":"333333","profile_use_background_image":true,"profile_image_url":"http:\/\/pbs.twimg.com\/profile_images\/378800000480470809\/65509142e331747b271786274de895fc_normal.jpeg","profile_image_url_https":"https:\/\/pbs.twimg.com\/profile_images\/378800000480470809\/65509142e331747b271786274de895fc_normal.jpeg","default_profile":true,"default_profile_image":false,"following":null,"follow_request_sent":null,"notifications":null},"geo":null,"coordinates":null,"place":null,"contributors":null,"is_quote_status":false,"quote_count":1,"reply_count":1,"retweet_count":3,"favorite_count":7,"entities":{"hashtags":[],"urls":[{"url":"https:\/\/t.co\/Glb9nJbFpI","expanded_url":"https:\/\/www.asahi.com\/articles\/DA3S13862379.html","display_url":"asahi.com\/articles\/DA3S1\u2026","indices":[87,110]}],"user_mentions":[],"symbols":[]},"favorited":false,"retweeted":false,"possibly_sensitive":false,"filter_level":"low","lang":"ja"},"quoted_status_permalink":{"url":"https:\/\/t.co\/qlSq49Atpj","expanded":"https:\/\/twitter.com\/maki_okubo\/status\/1088995851316293632","display":"twitter.com\/maki_okubo\/sta\u2026"},"is_quote_status":true,"extended_tweet":{"full_text":"\u3053\u306e\u671d\u65e5\u65b0\u805e\u306e\u8a18\u8005\u306f\u4f0a\u85e4\u548c\u5b50\u542b\u3081\u3066\u3001\u6839\u62e0\u306e\u306a\u3044\u30c7\u30de\u3084\u5dee\u5225\u306e\u652f\u63f4\u8005\u3060\u304b\u3089\u3069\u3046\u3057\u3088\u3046\u3082\u306a\u3044\u306a\u3002 #MeToo \u304c\u65e5\u672c\u3067\u5e83\u304c\u3089\u306a\u3044\u7406\u7531\u3068\u3057\u3066\u3001\u3053\u3046\u3044\u3063\u305f\u30c0\u30e1\u306a\u8a18\u8005\u306e\u305b\u3044\u3002\u3061\u3083\u3093\u3068\u6d3b\u52d5\u3057\u3066\u3044\u308b\u4eba\u3092\u53d6\u308a\u4e0a\u3052\u305a\u3001\u5b89\u6613\u306b\u3059\u3050\u30a2\u30af\u30bb\u30b9\u3067\u304d\u308b\u4eba\u3092\u4f7f\u3046\u3053\u3068\u3067\u9593\u9055\u3046\u3002 https:\/\/t.co\/qlSq49Atpj","display_text_range":[0,123],"entities":{"hashtags":[{"text":"MeToo","indices":[46,52]}],"urls":[{"url":"https:\/\/t.co\/qlSq49Atpj","expanded_url":"https:\/\/twitter.com\/maki_okubo\/status\/1088995851316293632","display_url":"twitter.com\/maki_okubo\/sta\u2026","indices":[124,147]}],"user_mentions":[],"symbols":[]}},"quote_count":1,"reply_count":0,"retweet_count":32,"favorite_count":17,"entities":{"hashtags":[{"text":"MeToo","indices":[46,52]}],"urls":[{"url":"https:\/\/t.co\/20LjP3Z6K3","expanded_url":"https:\/\/twitter.com\/i\/web\/status\/1089347362076512256","display_url":"twitter.com\/i\/web\/status\/1\u2026","indices":[117,140]}],"user_mentions":[],"symbols":[]},"favorited":false,"retweeted":false,"possibly_sensitive":false,"filter_level":"low","lang":"ja"},"quoted_status_id":1088995851316293632,"quoted_status_id_str":"1088995851316293632","quoted_status":{"created_at":"Sat Jan 26 03:03:38 +0000 2019","id":1088995851316293632,"id_str":"1088995851316293632","text":"\u56f0\u96e3\u3092\u62b1\u3048\u308b\u5c11\u5973\u305f\u3061\u306b\u5bc4\u308a\u6dfb\u3046\u4ec1\u85e4\u5922\u4e43\u3055\u3093\u306e\u3053\u3068\u3092\u66f8\u304d\u307e\u3057\u305f\u2192\uff08\u30d5\u30ed\u30f3\u30c8\u30e9\u30f3\u30ca\u30fc\uff09\u4e00\u822c\u793e\u56e3\u6cd5\u4eba\u300c\uff23\uff4f\uff4c\uff41\uff42\uff4f\u300d\u4ee3\u8868\u30fb\u4ec1\u85e4\u5922\u4e43\u3055\u3093\u3000\u73fe\u4ee3\u3092\u3055\u307e\u3088\u3046\u5c11\u5973\u305f\u3061\u3068\uff1a\u671d\u65e5\u65b0\u805e\u30c7\u30b8\u30bf\u30eb https:\/\/t.co\/Glb9nJbFpI","source":"\u003ca href=\"http:\/\/twitter.com\" rel=\"nofollow\"\u003eTwitter Web Client\u003c\/a\u003e","truncated":false,"in_reply_to_status_id":null,"in_reply_to_status_id_str":null,"in_reply_to_user_id":null,"in_reply_to_user_id_str":null,"in_reply_to_screen_name":null,"user":{"id":1612281888,"id_str":"1612281888","name":"\u5927\u4e45\u4fdd\u771f\u7d00","screen_name":"maki_okubo","location":null,"url":"http:\/\/www.asahi.com\/","description":"\u671d\u65e5\u65b0\u805e\u7de8\u96c6\u59d4\u54e1\u3002\uff11\uff19\uff18\uff17\u5e74\u304b\u3089\u8a18\u8005\u3092\u3057\u3066\u3044\u307e\u3059\u3002\u304a\u3082\u306b\u793e\u4f1a\u90e8\u7551\u3092\u6b69\u3044\u3066\u304d\u307e\u3057\u305f\u3002\u5e02\u4e95\u306e\u4eba\u3005\u306e\u55b6\u307f\u3001\u3075\u3064\u3046\u306e\u4eba\u305f\u3061\u306e\u3053\u3068\u3092\u66f8\u304d\u305f\u3044\u3068\u601d\u3063\u3066\u304d\u307e\u3057\u305f\u3002\u6c34\u306e\u4e2d\u306f\u5f97\u610f\u3067\u3059\u3002\u6295\u7a3f\u5185\u5bb9\u306f\u671d\u65e5\u65b0\u805e\u3092\u4ee3\u8868\u3059\u308b\u3082\u306e\u3067\u306f\u306a\u304f\u3001\u30ea\u30f3\u30af\u3084\uff32\uff34\u306f\u5fc5\u305a\u3057\u3082\u5185\u5bb9\u306b\u8cdb\u610f\u3092\u793a\u3059\u3082\u306e\u3067\u306f\u3042\u308a\u307e\u305b\u3093\u3002\u3054\u4e86\u627f\u304f\u3060\u3055\u3044\u3002","translator_type":"none","protected":false,"verified":true,"followers_count":3547,"friends_count":275,"listed_count":122,"favourites_count":168,"statuses_count":990,"created_at":"Mon Jul 22 08:02:32 +0000 2013","utc_offset":null,"time_zone":null,"geo_enabled":false,"lang":"ja","contributors_enabled":false,"is_translator":false,"profile_background_color":"C0DEED","profile_background_image_url":"http:\/\/abs.twimg.com\/images\/themes\/theme1\/bg.png","profile_background_image_url_https":"https:\/\/abs.twimg.com\/images\/themes\/theme1\/bg.png","profile_background_tile":false,"profile_link_color":"1DA1F2","profile_sidebar_border_color":"C0DEED","profile_sidebar_fill_color":"DDEEF6","profile_text_color":"333333","profile_use_background_image":true,"profile_image_url":"http:\/\/pbs.twimg.com\/profile_images\/378800000480470809\/65509142e331747b271786274de895fc_normal.jpeg","profile_image_url_https":"https:\/\/pbs.twimg.com\/profile_images\/378800000480470809\/65509142e331747b271786274de895fc_normal.jpeg","default_profile":true,"default_profile_image":false,"following":null,"follow_request_sent":null,"notifications":null},"geo":null,"coordinates":null,"place":null,"contributors":null,"is_quote_status":false,"quote_count":1,"reply_count":1,"retweet_count":3,"favorite_count":7,"entities":{"hashtags":[],"urls":[{"url":"https:\/\/t.co\/Glb9nJbFpI","expanded_url":"https:\/\/www.asahi.com\/articles\/DA3S13862379.html","display_url":"asahi.com\/articles\/DA3S1\u2026","indices":[87,110]}],"user_mentions":[],"symbols":[]},"favorited":false,"retweeted":false,"possibly_sensitive":false,"filter_level":"low","lang":"ja"},"quoted_status_permalink":{"url":"https:\/\/t.co\/qlSq49Atpj","expanded":"https:\/\/twitter.com\/maki_okubo\/status\/1088995851316293632","display":"twitter.com\/maki_okubo\/sta\u2026"},"is_quote_status":true,"quote_count":0,"reply_count":0,"retweet_count":0,"favorite_count":0,"entities":{"hashtags":[{"text":"MeToo","indices":[56,62]}],"urls":[],"user_mentions":[{"screen_name":"skd7","name":"\u3084\u3093","id":40851097,"id_str":"40851097","indices":[3,8]}],"symbols":[]},"favorited":false,"retweeted":false,"filter_level":"low","lang":"ja","timestamp_ms":"1548571286547"}
{"created_at":"Sun Jan 27 06:41:28 +0000 2019","id":1089413060027133952,"id_str":"1089413060027133952","text":"RT @comednDRichards: #MeToo #Romance https:\/\/t.co\/z1CILoxTzh","source":"\u003ca href=\"http:\/\/twitter.com\/download\/android\" rel=\"nofollow\"\u003eTwitter for Android\u003c\/a\u003e","truncated":false,"in_reply_to_status_id":null,"in_reply_to_status_id_str":null,"in_reply_to_user_id":null,"in_reply_to_user_id_str":null,"in_reply_to_screen_name":null,"user":{"id":472312943,"id_str":"472312943","name":"Marlon Mpamize\u2122","screen_name":"MarlonMpamize","location":"Kampala, Uganda","url":null,"description":"Everything LFC and Raikkonen.","translator_type":"none","protected":false,"verified":false,"followers_count":258,"friends_count":268,"listed_count":4,"favourites_count":2862,"statuses_count":5714,"created_at":"Mon Jan 23 20:33:56 +0000 2012","utc_offset":null,"time_zone":null,"geo_enabled":true,"lang":"en","contributors_enabled":false,"is_translator":false,"profile_background_color":"131516","profile_background_image_url":"http:\/\/abs.twimg.com\/images\/themes\/theme14\/bg.gif","profile_background_image_url_https":"https:\/\/abs.twimg.com\/images\/themes\/theme14\/bg.gif","profile_background_tile":true,"profile_link_color":"009999","profile_sidebar_border_color":"FFFFFF","profile_sidebar_fill_color":"EFEFEF","profile_text_color":"333333","profile_use_background_image":true,"profile_image_url":"http:\/\/pbs.twimg.com\/profile_images\/3713714529\/adc0cb947d1c4437c7bd7d9cdff2049a_normal.jpeg","profile_image_url_https":"https:\/\/pbs.twimg.com\/profile_images\/3713714529\/adc0cb947d1c4437c7bd7d9cdff2049a_normal.jpeg","profile_banner_url":"https:\/\/pbs.twimg.com\/profile_banners\/472312943\/1387562838","default_profile":false,"default_profile_image":false,"following":null,"follow_request_sent":null,"notifications":null},"geo":null,"coordinates":null,"place":null,"contributors":null,"retweeted_status":{"created_at":"Sun Jan 27 01:48:15 +0000 2019","id":1089339268592529408,"id_str":"1089339268592529408","text":"#MeToo #Romance https:\/\/t.co\/z1CILoxTzh","display_text_range":[0,15],"source":"\u003ca href=\"http:\/\/twitter.com\/download\/android\" rel=\"nofollow\"\u003eTwitter for Android\u003c\/a\u003e","truncated":false,"in_reply_to_status_id":null,"in_reply_to_status_id_str":null,"in_reply_to_user_id":null,"in_reply_to_user_id_str":null,"in_reply_to_screen_name":null,"user":{"id":928946677,"id_str":"928946677","name":"Derek Richards","screen_name":"comednDRichards","location":"Las Vegas","url":"http:\/\/www.derekrichards.com","description":"Stand up comedian. Irish whiskey slayer. Detroit native. Founder of  @irishcomedytour. My new book \u2018Whiskey, Cancer & Bad Decisions\u2019 is available now on Amazon!","translator_type":"none","protected":false,"verified":false,"followers_count":3801,"friends_count":4105,"listed_count":85,"favourites_count":3772,"statuses_count":10923,"created_at":"Tue Nov 06 03:44:21 +0000 2012","utc_offset":null,"time_zone":null,"geo_enabled":true,"lang":"en","contributors_enabled":false,"is_translator":false,"profile_background_color":"C0DEED","profile_background_image_url":"http:\/\/abs.twimg.com\/images\/themes\/theme1\/bg.png","profile_background_image_url_https":"https:\/\/abs.twimg.com\/images\/themes\/theme1\/bg.png","profile_background_tile":false,"profile_link_color":"1DA1F2","profile_sidebar_border_color":"C0DEED","profile_sidebar_fill_color":"DDEEF6","profile_text_color":"333333","profile_use_background_image":true,"profile_image_url":"http:\/\/pbs.twimg.com\/profile_images\/1056550637389996032\/Ku27M5t3_normal.jpg","profile_image_url_https":"https:\/\/pbs.twimg.com\/profile_images\/1056550637389996032\/Ku27M5t3_normal.jpg","profile_banner_url":"https:\/\/pbs.twimg.com\/profile_banners\/928946677\/1540674093","default_profile":true,"default_profile_image":false,"following":null,"follow_request_sent":null,"notifications":null},"geo":null,"coordinates":null,"place":{"id":"9531d4e3bbafc09d","url":"https:\/\/api.twitter.com\/1.1\/geo\/id\/9531d4e3bbafc09d.json","place_type":"city","name":"Oklahoma City","full_name":"Oklahoma City, OK","country_code":"US","country":"United States","bounding_box":{"type":"Polygon","coordinates":[[[-97.768683,35.290722],[-97.768683,35.674965],[-97.335639,35.674965],[-97.335639,35.290722]]]},"attributes":{}},"contributors":null,"is_quote_status":false,"quote_count":0,"reply_count":0,"retweet_count":2,"favorite_count":16,"entities":{"hashtags":[{"text":"MeToo","indices":[0,6]},{"text":"Romance","indices":[7,15]}],"urls":[],"user_mentions":[],"symbols":[],"media":[{"id":1089339262577762305,"id_str":"1089339262577762305","indices":[16,39],"media_url":"http:\/\/pbs.twimg.com\/media\/Dx4cSanVYAEpLvp.jpg","media_url_https":"https:\/\/pbs.twimg.com\/media\/Dx4cSanVYAEpLvp.jpg","url":"https:\/\/t.co\/z1CILoxTzh","display_url":"pic.twitter.com\/z1CILoxTzh","expanded_url":"https:\/\/twitter.com\/comednDRichards\/status\/1089339268592529408\/photo\/1","type":"photo","sizes":{"thumb":{"w":150,"h":150,"resize":"crop"},"medium":{"w":720,"h":885,"resize":"fit"},"large":{"w":720,"h":885,"resize":"fit"},"small":{"w":553,"h":680,"resize":"fit"}}}]},"extended_entities":{"media":[{"id":1089339262577762305,"id_str":"1089339262577762305","indices":[16,39],"media_url":"http:\/\/pbs.twimg.com\/media\/Dx4cSanVYAEpLvp.jpg","media_url_https":"https:\/\/pbs.twimg.com\/media\/Dx4cSanVYAEpLvp.jpg","url":"https:\/\/t.co\/z1CILoxTzh","display_url":"pic.twitter.com\/z1CILoxTzh","expanded_url":"https:\/\/twitter.com\/comednDRichards\/status\/1089339268592529408\/photo\/1","type":"photo","sizes":{"thumb":{"w":150,"h":150,"resize":"crop"},"medium":{"w":720,"h":885,"resize":"fit"},"large":{"w":720,"h":885,"resize":"fit"},"small":{"w":553,"h":680,"resize":"fit"}}}]},"favorited":false,"retweeted":false,"possibly_sensitive":false,"filter_level":"low","lang":"und"},"is_quote_status":false,"quote_count":0,"reply_count":0,"retweet_count":0,"favorite_count":0,"entities":{"hashtags":[{"text":"MeToo","indices":[21,27]},{"text":"Romance","indices":[28,36]}],"urls":[],"user_mentions":[{"screen_name":"comednDRichards","name":"Derek Richards","id":928946677,"id_str":"928946677","indices":[3,19]}],"symbols":[],"media":[{"id":1089339262577762305,"id_str":"1089339262577762305","indices":[37,60],"media_url":"http:\/\/pbs.twimg.com\/media\/Dx4cSanVYAEpLvp.jpg","media_url_https":"https:\/\/pbs.twimg.com\/media\/Dx4cSanVYAEpLvp.jpg","url":"https:\/\/t.co\/z1CILoxTzh","display_url":"pic.twitter.com\/z1CILoxTzh","expanded_url":"https:\/\/twitter.com\/comednDRichards\/status\/1089339268592529408\/photo\/1","type":"photo","sizes":{"thumb":{"w":150,"h":150,"resize":"crop"},"medium":{"w":720,"h":885,"resize":"fit"},"large":{"w":720,"h":885,"resize":"fit"},"small":{"w":553,"h":680,"resize":"fit"}},"source_status_id":1089339268592529408,"source_status_id_str":"1089339268592529408","source_user_id":928946677,"source_user_id_str":"928946677"}]},"extended_entities":{"media":[{"id":1089339262577762305,"id_str":"1089339262577762305","indices":[37,60],"media_url":"http:\/\/pbs.twimg.com\/media\/Dx4cSanVYAEpLvp.jpg","media_url_https":"https:\/\/pbs.twimg.com\/media\/Dx4cSanVYAEpLvp.jpg","url":"https:\/\/t.co\/z1CILoxTzh","display_url":"pic.twitter.com\/z1CILoxTzh","expanded_url":"https:\/\/twitter.com\/comednDRichards\/status\/1089339268592529408\/photo\/1","type":"photo","sizes":{"thumb":{"w":150,"h":150,"resize":"crop"},"medium":{"w":720,"h":885,"resize":"fit"},"large":{"w":720,"h":885,"resize":"fit"},"small":{"w":553,"h":680,"resize":"fit"}},"source_status_id":1089339268592529408,"source_status_id_str":"1089339268592529408","source_user_id":928946677,"source_user_id_str":"928946677"}]},"favorited":false,"retweeted":false,"possibly_sensitive":false,"filter_level":"low","lang":"und","timestamp_ms":"1548571288483"}
{"created_at":"Sun Jan 27 06:41:37 +0000 2019","id":1089413096643342337,"id_str":"1089413096643342337","text":"RT @johnkgalbraith: Please share this article!!\n#share #JusticeForMahohon #JusticeForMaho #ngt48 #ngt  #inapooh0725 #criminal #crime #cnn #\u2026","source":"\u003ca href=\"http:\/\/twitter.com\/download\/iphone\" rel=\"nofollow\"\u003eTwitter for iPhone\u003c\/a\u003e","truncated":false,"in_reply_to_status_id":null,"in_reply_to_status_id_str":null,"in_reply_to_user_id":null,"in_reply_to_user_id_str":null,"in_reply_to_screen_name":null,"user":{"id":1082059677549047808,"id_str":"1082059677549047808","name":"\u5c71\u53e3\u771f\u5e06@NGT48\u3092\u52a9\u3051\u305f\u3044","screen_name":"yamaguchi_maho_","location":null,"url":null,"description":"#NGT48 #\u5c71\u53e3\u771f\u5e06 \u3055\u3093\u3092\u52a9\u3051\u305f\u3044\u3002\u7686\u3055\u3093\u306e\u3054\u5354\u529b\u304a\u9858\u3044\u81f4\u3057\u307e\u3059\ud83d\ude2d #justiceformahoh\u25cbn \u306f \u30a2\u30ab\u30a6\u30f3\u30c8\u30ed\u30c3\u25cb\u306b\u306a\u308b\u53ef\u80fd\u6027\u304c\u3042\u308a\u307e\u3059\u3002\u6c17\u3092\u3064\u3051\u3066\u3002@Maho_yamaguchi_ \u306f\u51cd\u7d50\u3055\u308c\u307e\u3057\u305f\u3002","translator_type":"none","protected":false,"verified":false,"followers_count":34,"friends_count":49,"listed_count":0,"favourites_count":1490,"statuses_count":892,"created_at":"Sun Jan 06 23:41:45 +0000 2019","utc_offset":null,"time_zone":null,"geo_enabled":false,"lang":"en","contributors_enabled":false,"is_translator":false,"profile_background_color":"F5F8FA","profile_background_image_url":"","profile_background_image_url_https":"","profile_background_tile":false,"profile_link_color":"1DA1F2","profile_sidebar_border_color":"C0DEED","profile_sidebar_fill_color":"DDEEF6","profile_text_color":"333333","profile_use_background_image":true,"profile_image_url":"http:\/\/pbs.twimg.com\/profile_images\/1086121252379492357\/GJWDEZjq_normal.jpg","profile_image_url_https":"https:\/\/pbs.twimg.com\/profile_images\/1086121252379492357\/GJWDEZjq_normal.jpg","profile_banner_url":"https:\/\/pbs.twimg.com\/profile_banners\/1082059677549047808\/1547786461","default_profile":true,"default_profile_image":false,"following":null,"follow_request_sent":null,"notifications":null},"geo":null,"coordinates":null,"place":null,"contributors":null,"retweeted_status":{"created_at":"Sat Jan 26 15:04:20 +0000 2019","id":1089177221162385408,"id_str":"1089177221162385408","text":"Please share this article!!\n#share #JusticeForMahohon #JusticeForMaho #ngt48 #ngt  #inapooh0725 #criminal #crime\u2026 https:\/\/t.co\/hl3GbsQBFh","display_text_range":[0,140],"source":"\u003ca href=\"http:\/\/twitter.com\/download\/iphone\" rel=\"nofollow\"\u003eTwitter for iPhone\u003c\/a\u003e","truncated":true,"in_reply_to_status_id":null,"in_reply_to_status_id_str":null,"in_reply_to_user_id":null,"in_reply_to_user_id_str":null,"in_reply_to_screen_name":null,"user":{"id":131222694,"id_str":"131222694","name":"\u30a2\u30c3\u30ad\u30fc (\u0411\u043e\u0440\u0438\u0441 \u041c\u0438\u0445\u0430\u0439\u043b\u043e\u0432\u0438\u0447 \u041a\u0443\u043b\u0438\u043a\u043e\u0432)","screen_name":"johnkgalbraith","location":"\u65b0\u6f5f\u3001\u6771\u4eac\u3001\u798f\u5ca1\u3001\u9577\u5d0e","url":null,"description":"\u90fd\u5185\u67d0\u5927\u5b66\u75c5\u9662\u306e\u5916\u79d1\u533b\u3002\u6545\u90f7\uff1a\u65b0\u6f5f\u30fb\u6771\u4eac\u30fb\u5317\u90e8\u4e5d\u5dde(\u798f\u5ca1\u30fb\u9577\u5d0e)\u3001\u9280\u5ea7\u306e\u30d0\u30fc\u3002AMSA , IFMSA\u306eOB \u3002\u5143\u0421\u0435\u0432\u0435\u0440\u043d\u0430\u044f \u041a\u043e\u0440\u0435\u044f \u041e\u0442\u0432\u0435\u0442\u0441\u0442\u0432\u0435\u043d\u043d\u043e\u0435 \u043b\u0438\u0446\u043e\uff1a\u0411\u043e\u0440\u0438\u0441 \u041c\u0438\u0445\u0430\u0439\u043b\u043e\u0432\u0438\u0447 \u041a\u0443\u043b\u0438\u043a\u043e\u0432\u3002\u8208\u5473\u3042\u308b\u3053\u3068 : \u5730\u57df\u533b\u7642\u3001\u533b\u7642\u653f\u7b56\u5b66\u3001\u5b89\u5168\u4fdd\u969c\u3001\u5730\u57df\u6d3b\u6027\u5316\u3001\u82e5\u5e74\u8005\u306e\u8ca7\u56f0\u554f\u984c\u3001\u6027\u554f\u984c\u3002","translator_type":"none","protected":false,"verified":false,"followers_count":177,"friends_count":253,"listed_count":1,"favourites_count":176,"statuses_count":1020,"created_at":"Fri Apr 09 16:55:01 +0000 2010","utc_offset":null,"time_zone":null,"geo_enabled":true,"lang":"ja","contributors_enabled":false,"is_translator":false,"profile_background_color":"000000","profile_background_image_url":"http:\/\/abs.twimg.com\/images\/themes\/theme1\/bg.png","profile_background_image_url_https":"https:\/\/abs.twimg.com\/images\/themes\/theme1\/bg.png","profile_background_tile":false,"profile_link_color":"4A913C","profile_sidebar_border_color":"000000","profile_sidebar_fill_color":"000000","profile_text_color":"000000","profile_use_background_image":false,"profile_image_url":"http:\/\/pbs.twimg.com\/profile_images\/1089137267027828736\/scEPNRQ__normal.jpg","profile_image_url_https":"https:\/\/pbs.twimg.com\/profile_images\/1089137267027828736\/scEPNRQ__normal.jpg","profile_banner_url":"https:\/\/pbs.twimg.com\/profile_banners\/131222694\/1526952437","default_profile":false,"default_profile_image":false,"following":null,"follow_request_sent":null,"notifications":null},"geo":null,"coordinates":null,"place":null,"contributors":null,"quoted_status_id":1089174691703488512,"quoted_status_id_str":"1089174691703488512","quoted_status":{"created_at":"Sat Jan 26 14:54:17 +0000 2019","id":1089174691703488512,"id_str":"1089174691703488512","text":"Please read this article, and think about what\u2019s right, what justice is.\nHelp us reveal the whole truth by sharing\u2026 https:\/\/t.co\/g3Rx7znqxr","display_text_range":[0,140],"source":"\u003ca href=\"http:\/\/twitter.com\" rel=\"nofollow\"\u003eTwitter Web Client\u003c\/a\u003e","truncated":true,"in_reply_to_status_id":null,"in_reply_to_status_id_str":null,"in_reply_to_user_id":null,"in_reply_to_user_id_str":null,"in_reply_to_screen_name":null,"user":{"id":1086678143610441728,"id_str":"1086678143610441728","name":"nanj","screen_name":"nanj16990709","location":null,"url":null,"description":"#JusticeForMahohon \u52dd\u624b\u306b\u30d5\u30a9\u30ed\u30fc\u3057\u307e\u3059 \u76ee\u969c\u308a\u306a\u3089\u30d6\u30ed\u30c3\u30af\u3057\u3066\u4e0b\u3055\u3044 \u3053\u306e\u4e8b\u4ef6\u304c\u89e3\u6c7a\u3059\u308c\u3070\u6d88\u3057\u307e\u3059\u3002","translator_type":"none","protected":false,"verified":false,"followers_count":257,"friends_count":462,"listed_count":2,"favourites_count":13,"statuses_count":32,"created_at":"Sat Jan 19 17:33:53 +0000 2019","utc_offset":null,"time_zone":null,"geo_enabled":false,"lang":"ja","contributors_enabled":false,"is_translator":false,"profile_background_color":"F5F8FA","profile_background_image_url":"","profile_background_image_url_https":"","profile_background_tile":false,"profile_link_color":"1DA1F2","profile_sidebar_border_color":"C0DEED","profile_sidebar_fill_color":"DDEEF6","profile_text_color":"333333","profile_use_background_image":true,"profile_image_url":"http:\/\/pbs.twimg.com\/profile_images\/1087777297099149312\/lUFLC5qD_normal.jpg","profile_image_url_https":"https:\/\/pbs.twimg.com\/profile_images\/1087777297099149312\/lUFLC5qD_normal.jpg","default_profile":true,"default_profile_image":false,"following":null,"follow_request_sent":null,"notifications":null},"geo":null,"coordinates":null,"place":null,"contributors":null,"is_quote_status":false,"extended_tweet":{"full_text":"Please read this article, and think about what\u2019s right, what justice is.\nHelp us reveal the whole truth by sharing this story.\nWe NEED YOUR HELP.\n\n#PleaseHelp #JusticeForMahohon #share #sorrynotsorry #NeverForge #MeToo #YamaguchiMaho #\u5c71\u53e3\u771f\u5e06 https:\/\/t.co\/R6yXUZsV7M","display_text_range":[0,239],"entities":{"hashtags":[{"text":"PleaseHelp","indices":[147,158]},{"text":"JusticeForMahohon","indices":[159,177]},{"text":"share","indices":[178,184]},{"text":"sorrynotsorry","indices":[185,199]},{"text":"NeverForge","indices":[200,211]},{"text":"MeToo","indices":[212,218]},{"text":"YamaguchiMaho","indices":[219,233]},{"text":"\u5c71\u53e3\u771f\u5e06","indices":[234,239]}],"urls":[],"user_mentions":[],"symbols":[],"media":[{"id":1089174589890940928,"id_str":"1089174589890940928","indices":[240,263],"media_url":"http:\/\/pbs.twimg.com\/media\/Dx2GhNDU0AAoByc.jpg","media_url_https":"https:\/\/pbs.twimg.com\/media\/Dx2GhNDU0AAoByc.jpg","url":"https:\/\/t.co\/R6yXUZsV7M","display_url":"pic.twitter.com\/R6yXUZsV7M","expanded_url":"https:\/\/twitter.com\/nanj16990709\/status\/1089174691703488512\/photo\/1","type":"photo","sizes":{"thumb":{"w":150,"h":150,"resize":"crop"},"small":{"w":375,"h":680,"resize":"fit"},"large":{"w":1129,"h":2048,"resize":"fit"},"medium":{"w":662,"h":1200,"resize":"fit"}}},{"id":1089174614029217792,"id_str":"1089174614029217792","indices":[240,263],"media_url":"http:\/\/pbs.twimg.com\/media\/Dx2Gim-VsAA8YuU.jpg","media_url_https":"https:\/\/pbs.twimg.com\/media\/Dx2Gim-VsAA8YuU.jpg","url":"https:\/\/t.co\/R6yXUZsV7M","display_url":"pic.twitter.com\/R6yXUZsV7M","expanded_url":"https:\/\/twitter.com\/nanj16990709\/status\/1089174691703488512\/photo\/1","type":"photo","sizes":{"thumb":{"w":150,"h":150,"resize":"crop"},"medium":{"w":661,"h":1200,"resize":"fit"},"large":{"w":1128,"h":2048,"resize":"fit"},"small":{"w":375,"h":680,"resize":"fit"}}},{"id":1089174623302836225,"id_str":"1089174623302836225","indices":[240,263],"media_url":"http:\/\/pbs.twimg.com\/media\/Dx2GjJhV4AESKlN.jpg","media_url_https":"https:\/\/pbs.twimg.com\/media\/Dx2GjJhV4AESKlN.jpg","url":"https:\/\/t.co\/R6yXUZsV7M","display_url":"pic.twitter.com\/R6yXUZsV7M","expanded_url":"https:\/\/twitter.com\/nanj16990709\/status\/1089174691703488512\/photo\/1","type":"photo","sizes":{"thumb":{"w":150,"h":150,"resize":"crop"},"medium":{"w":660,"h":1200,"resize":"fit"},"small":{"w":374,"h":680,"resize":"fit"},"large":{"w":1127,"h":2048,"resize":"fit"}}},{"id":1089174638012157952,"id_str":"1089174638012157952","indices":[240,263],"media_url":"http:\/\/pbs.twimg.com\/media\/Dx2GkAUUUAAlQVM.jpg","media_url_https":"https:\/\/pbs.twimg.com\/media\/Dx2GkAUUUAAlQVM.jpg","url":"https:\/\/t.co\/R6yXUZsV7M","display_url":"pic.twitter.com\/R6yXUZsV7M","expanded_url":"https:\/\/twitter.com\/nanj16990709\/status\/1089174691703488512\/photo\/1","type":"photo","sizes":{"large":{"w":1164,"h":2048,"resize":"fit"},"thumb":{"w":150,"h":150,"resize":"crop"},"small":{"w":386,"h":680,"resize":"fit"},"medium":{"w":682,"h":1200,"resize":"fit"}}}]},"extended_entities":{"media":[{"id":1089174589890940928,"id_str":"1089174589890940928","indices":[240,263],"media_url":"http:\/\/pbs.twimg.com\/media\/Dx2GhNDU0AAoByc.jpg","media_url_https":"https:\/\/pbs.twimg.com\/media\/Dx2GhNDU0AAoByc.jpg","url":"https:\/\/t.co\/R6yXUZsV7M","display_url":"pic.twitter.com\/R6yXUZsV7M","expanded_url":"https:\/\/twitter.com\/nanj16990709\/status\/1089174691703488512\/photo\/1","type":"photo","sizes":{"thumb":{"w":150,"h":150,"resize":"crop"},"small":{"w":375,"h":680,"resize":"fit"},"large":{"w":1129,"h":2048,"resize":"fit"},"medium":{"w":662,"h":1200,"resize":"fit"}}},{"id":1089174614029217792,"id_str":"1089174614029217792","indices":[240,263],"media_url":"http:\/\/pbs.twimg.com\/media\/Dx2Gim-VsAA8YuU.jpg","media_url_https":"https:\/\/pbs.twimg.com\/media\/Dx2Gim-VsAA8YuU.jpg","url":"https:\/\/t.co\/R6yXUZsV7M","display_url":"pic.twitter.com\/R6yXUZsV7M","expanded_url":"https:\/\/twitter.com\/nanj16990709\/status\/1089174691703488512\/photo\/1","type":"photo","sizes":{"thumb":{"w":150,"h":150,"resize":"crop"},"medium":{"w":661,"h":1200,"resize":"fit"},"large":{"w":1128,"h":2048,"resize":"fit"},"small":{"w":375,"h":680,"resize":"fit"}}},{"id":1089174623302836225,"id_str":"1089174623302836225","indices":[240,263],"media_url":"http:\/\/pbs.twimg.com\/media\/Dx2GjJhV4AESKlN.jpg","media_url_https":"https:\/\/pbs.twimg.com\/media\/Dx2GjJhV4AESKlN.jpg","url":"https:\/\/t.co\/R6yXUZsV7M","display_url":"pic.twitter.com\/R6yXUZsV7M","expanded_url":"https:\/\/twitter.com\/nanj16990709\/status\/1089174691703488512\/photo\/1","type":"photo","sizes":{"thumb":{"w":150,"h":150,"resize":"crop"},"medium":{"w":660,"h":1200,"resize":"fit"},"small":{"w":374,"h":680,"resize":"fit"},"large":{"w":1127,"h":2048,"resize":"fit"}}},{"id":1089174638012157952,"id_str":"1089174638012157952","indices":[240,263],"media_url":"http:\/\/pbs.twimg.com\/media\/Dx2GkAUUUAAlQVM.jpg","media_url_https":"https:\/\/pbs.twimg.com\/media\/Dx2GkAUUUAAlQVM.jpg","url":"https:\/\/t.co\/R6yXUZsV7M","display_url":"pic.twitter.com\/R6yXUZsV7M","expanded_url":"https:\/\/twitter.com\/nanj16990709\/status\/1089174691703488512\/photo\/1","type":"photo","sizes":{"large":{"w":1164,"h":2048,"resize":"fit"},"thumb":{"w":150,"h":150,"resize":"crop"},"small":{"w":386,"h":680,"resize":"fit"},"medium":{"w":682,"h":1200,"resize":"fit"}}}]}},"quote_count":19,"reply_count":8,"retweet_count":357,"favorite_count":331,"entities":{"hashtags":[],"urls":[{"url":"https:\/\/t.co\/g3Rx7znqxr","expanded_url":"https:\/\/twitter.com\/i\/web\/status\/1089174691703488512","display_url":"twitter.com\/i\/web\/status\/1\u2026","indices":[116,139]}],"user_mentions":[],"symbols":[]},"favorited":false,"retweeted":false,"possibly_sensitive":false,"filter_level":"low","lang":"en"},"quoted_status_permalink":{"url":"https:\/\/t.co\/EQtVcczyyD","expanded":"https:\/\/twitter.com\/nanj16990709\/status\/1089174691703488512","display":"twitter.com\/nanj16990709\/s\u2026"},"is_quote_status":true,"extended_tweet":{"full_text":"Please share this article!!\n#share #JusticeForMahohon #JusticeForMaho #ngt48 #ngt  #inapooh0725 #criminal #crime #cnn #inapooh0725 #assault https:\/\/t.co\/EQtVcczyyD","display_text_range":[0,139],"entities":{"hashtags":[{"text":"share","indices":[28,34]},{"text":"JusticeForMahohon","indices":[35,53]},{"text":"JusticeForMaho","indices":[54,69]},{"text":"ngt48","indices":[70,76]},{"text":"ngt","indices":[77,81]},{"text":"inapooh0725","indices":[83,95]},{"text":"criminal","indices":[96,105]},{"text":"crime","indices":[106,112]},{"text":"cnn","indices":[113,117]},{"text":"inapooh0725","indices":[118,130]},{"text":"assault","indices":[131,139]}],"urls":[{"url":"https:\/\/t.co\/EQtVcczyyD","expanded_url":"https:\/\/twitter.com\/nanj16990709\/status\/1089174691703488512","display_url":"twitter.com\/nanj16990709\/s\u2026","indices":[140,163]}],"user_mentions":[],"symbols":[]}},"quote_count":0,"reply_count":0,"retweet_count":7,"favorite_count":9,"entities":{"hashtags":[{"text":"share","indices":[28,34]},{"text":"JusticeForMahohon","indices":[35,53]},{"text":"JusticeForMaho","indices":[54,69]},{"text":"ngt48","indices":[70,76]},{"text":"ngt","indices":[77,81]},{"text":"inapooh0725","indices":[83,95]},{"text":"criminal","indices":[96,105]},{"text":"crime","indices":[106,112]}],"urls":[{"url":"https:\/\/t.co\/hl3GbsQBFh","expanded_url":"https:\/\/twitter.com\/i\/web\/status\/1089177221162385408","display_url":"twitter.com\/i\/web\/status\/1\u2026","indices":[114,137]}],"user_mentions":[],"symbols":[]},"favorited":false,"retweeted":false,"possibly_sensitive":false,"filter_level":"low","lang":"en"},"quoted_status_id":1089174691703488512,"quoted_status_id_str":"1089174691703488512","quoted_status":{"created_at":"Sat Jan 26 14:54:17 +0000 2019","id":1089174691703488512,"id_str":"1089174691703488512","text":"Please read this article, and think about what\u2019s right, what justice is.\nHelp us reveal the whole truth by sharing\u2026 https:\/\/t.co\/g3Rx7znqxr","display_text_range":[0,140],"source":"\u003ca href=\"http:\/\/twitter.com\" rel=\"nofollow\"\u003eTwitter Web Client\u003c\/a\u003e","truncated":true,"in_reply_to_status_id":null,"in_reply_to_status_id_str":null,"in_reply_to_user_id":null,"in_reply_to_user_id_str":null,"in_reply_to_screen_name":null,"user":{"id":1086678143610441728,"id_str":"1086678143610441728","name":"nanj","screen_name":"nanj16990709","location":null,"url":null,"description":"#JusticeForMahohon \u52dd\u624b\u306b\u30d5\u30a9\u30ed\u30fc\u3057\u307e\u3059 \u76ee\u969c\u308a\u306a\u3089\u30d6\u30ed\u30c3\u30af\u3057\u3066\u4e0b\u3055\u3044 \u3053\u306e\u4e8b\u4ef6\u304c\u89e3\u6c7a\u3059\u308c\u3070\u6d88\u3057\u307e\u3059\u3002","translator_type":"none","protected":false,"verified":false,"followers_count":257,"friends_count":462,"listed_count":2,"favourites_count":13,"statuses_count":32,"created_at":"Sat Jan 19 17:33:53 +0000 2019","utc_offset":null,"time_zone":null,"geo_enabled":false,"lang":"ja","contributors_enabled":false,"is_translator":false,"profile_background_color":"F5F8FA","profile_background_image_url":"","profile_background_image_url_https":"","profile_background_tile":false,"profile_link_color":"1DA1F2","profile_sidebar_border_color":"C0DEED","profile_sidebar_fill_color":"DDEEF6","profile_text_color":"333333","profile_use_background_image":true,"profile_image_url":"http:\/\/pbs.twimg.com\/profile_images\/1087777297099149312\/lUFLC5qD_normal.jpg","profile_image_url_https":"https:\/\/pbs.twimg.com\/profile_images\/1087777297099149312\/lUFLC5qD_normal.jpg","default_profile":true,"default_profile_image":false,"following":null,"follow_request_sent":null,"notifications":null},"geo":null,"coordinates":null,"place":null,"contributors":null,"is_quote_status":false,"extended_tweet":{"full_text":"Please read this article, and think about what\u2019s right, what justice is.\nHelp us reveal the whole truth by sharing this story.\nWe NEED YOUR HELP.\n\n#PleaseHelp #JusticeForMahohon #share #sorrynotsorry #NeverForge #MeToo #YamaguchiMaho #\u5c71\u53e3\u771f\u5e06 https:\/\/t.co\/R6yXUZsV7M","display_text_range":[0,239],"entities":{"hashtags":[{"text":"PleaseHelp","indices":[147,158]},{"text":"JusticeForMahohon","indices":[159,177]},{"text":"share","indices":[178,184]},{"text":"sorrynotsorry","indices":[185,199]},{"text":"NeverForge","indices":[200,211]},{"text":"MeToo","indices":[212,218]},{"text":"YamaguchiMaho","indices":[219,233]},{"text":"\u5c71\u53e3\u771f\u5e06","indices":[234,239]}],"urls":[],"user_mentions":[],"symbols":[],"media":[{"id":1089174589890940928,"id_str":"1089174589890940928","indices":[240,263],"media_url":"http:\/\/pbs.twimg.com\/media\/Dx2GhNDU0AAoByc.jpg","media_url_https":"https:\/\/pbs.twimg.com\/media\/Dx2GhNDU0AAoByc.jpg","url":"https:\/\/t.co\/R6yXUZsV7M","display_url":"pic.twitter.com\/R6yXUZsV7M","expanded_url":"https:\/\/twitter.com\/nanj16990709\/status\/1089174691703488512\/photo\/1","type":"photo","sizes":{"thumb":{"w":150,"h":150,"resize":"crop"},"small":{"w":375,"h":680,"resize":"fit"},"large":{"w":1129,"h":2048,"resize":"fit"},"medium":{"w":662,"h":1200,"resize":"fit"}}},{"id":1089174614029217792,"id_str":"1089174614029217792","indices":[240,263],"media_url":"http:\/\/pbs.twimg.com\/media\/Dx2Gim-VsAA8YuU.jpg","media_url_https":"https:\/\/pbs.twimg.com\/media\/Dx2Gim-VsAA8YuU.jpg","url":"https:\/\/t.co\/R6yXUZsV7M","display_url":"pic.twitter.com\/R6yXUZsV7M","expanded_url":"https:\/\/twitter.com\/nanj16990709\/status\/1089174691703488512\/photo\/1","type":"photo","sizes":{"thumb":{"w":150,"h":150,"resize":"crop"},"medium":{"w":661,"h":1200,"resize":"fit"},"large":{"w":1128,"h":2048,"resize":"fit"},"small":{"w":375,"h":680,"resize":"fit"}}},{"id":1089174623302836225,"id_str":"1089174623302836225","indices":[240,263],"media_url":"http:\/\/pbs.twimg.com\/media\/Dx2GjJhV4AESKlN.jpg","media_url_https":"https:\/\/pbs.twimg.com\/media\/Dx2GjJhV4AESKlN.jpg","url":"https:\/\/t.co\/R6yXUZsV7M","display_url":"pic.twitter.com\/R6yXUZsV7M","expanded_url":"https:\/\/twitter.com\/nanj16990709\/status\/1089174691703488512\/photo\/1","type":"photo","sizes":{"thumb":{"w":150,"h":150,"resize":"crop"},"medium":{"w":660,"h":1200,"resize":"fit"},"small":{"w":374,"h":680,"resize":"fit"},"large":{"w":1127,"h":2048,"resize":"fit"}}},{"id":1089174638012157952,"id_str":"1089174638012157952","indices":[240,263],"media_url":"http:\/\/pbs.twimg.com\/media\/Dx2GkAUUUAAlQVM.jpg","media_url_https":"https:\/\/pbs.twimg.com\/media\/Dx2GkAUUUAAlQVM.jpg","url":"https:\/\/t.co\/R6yXUZsV7M","display_url":"pic.twitter.com\/R6yXUZsV7M","expanded_url":"https:\/\/twitter.com\/nanj16990709\/status\/1089174691703488512\/photo\/1","type":"photo","sizes":{"large":{"w":1164,"h":2048,"resize":"fit"},"thumb":{"w":150,"h":150,"resize":"crop"},"small":{"w":386,"h":680,"resize":"fit"},"medium":{"w":682,"h":1200,"resize":"fit"}}}]},"extended_entities":{"media":[{"id":1089174589890940928,"id_str":"1089174589890940928","indices":[240,263],"media_url":"http:\/\/pbs.twimg.com\/media\/Dx2GhNDU0AAoByc.jpg","media_url_https":"https:\/\/pbs.twimg.com\/media\/Dx2GhNDU0AAoByc.jpg","url":"https:\/\/t.co\/R6yXUZsV7M","display_url":"pic.twitter.com\/R6yXUZsV7M","expanded_url":"https:\/\/twitter.com\/nanj16990709\/status\/1089174691703488512\/photo\/1","type":"photo","sizes":{"thumb":{"w":150,"h":150,"resize":"crop"},"small":{"w":375,"h":680,"resize":"fit"},"large":{"w":1129,"h":2048,"resize":"fit"},"medium":{"w":662,"h":1200,"resize":"fit"}}},{"id":1089174614029217792,"id_str":"1089174614029217792","indices":[240,263],"media_url":"http:\/\/pbs.twimg.com\/media\/Dx2Gim-VsAA8YuU.jpg","media_url_https":"https:\/\/pbs.twimg.com\/media\/Dx2Gim-VsAA8YuU.jpg","url":"https:\/\/t.co\/R6yXUZsV7M","display_url":"pic.twitter.com\/R6yXUZsV7M","expanded_url":"https:\/\/twitter.com\/nanj16990709\/status\/1089174691703488512\/photo\/1","type":"photo","sizes":{"thumb":{"w":150,"h":150,"resize":"crop"},"medium":{"w":661,"h":1200,"resize":"fit"},"large":{"w":1128,"h":2048,"resize":"fit"},"small":{"w":375,"h":680,"resize":"fit"}}},{"id":1089174623302836225,"id_str":"1089174623302836225","indices":[240,263],"media_url":"http:\/\/pbs.twimg.com\/media\/Dx2GjJhV4AESKlN.jpg","media_url_https":"https:\/\/pbs.twimg.com\/media\/Dx2GjJhV4AESKlN.jpg","url":"https:\/\/t.co\/R6yXUZsV7M","display_url":"pic.twitter.com\/R6yXUZsV7M","expanded_url":"https:\/\/twitter.com\/nanj16990709\/status\/1089174691703488512\/photo\/1","type":"photo","sizes":{"thumb":{"w":150,"h":150,"resize":"crop"},"medium":{"w":660,"h":1200,"resize":"fit"},"small":{"w":374,"h":680,"resize":"fit"},"large":{"w":1127,"h":2048,"resize":"fit"}}},{"id":1089174638012157952,"id_str":"1089174638012157952","indices":[240,263],"media_url":"http:\/\/pbs.twimg.com\/media\/Dx2GkAUUUAAlQVM.jpg","media_url_https":"https:\/\/pbs.twimg.com\/media\/Dx2GkAUUUAAlQVM.jpg","url":"https:\/\/t.co\/R6yXUZsV7M","display_url":"pic.twitter.com\/R6yXUZsV7M","expanded_url":"https:\/\/twitter.com\/nanj16990709\/status\/1089174691703488512\/photo\/1","type":"photo","sizes":{"large":{"w":1164,"h":2048,"resize":"fit"},"thumb":{"w":150,"h":150,"resize":"crop"},"small":{"w":386,"h":680,"resize":"fit"},"medium":{"w":682,"h":1200,"resize":"fit"}}}]}},"quote_count":19,"reply_count":8,"retweet_count":357,"favorite_count":331,"entities":{"hashtags":[],"urls":[{"url":"https:\/\/t.co\/g3Rx7znqxr","expanded_url":"https:\/\/twitter.com\/i\/web\/status\/1089174691703488512","display_url":"twitter.com\/i\/web\/status\/1\u2026","indices":[116,139]}],"user_mentions":[],"symbols":[]},"favorited":false,"retweeted":false,"possibly_sensitive":false,"filter_level":"low","lang":"en"},"quoted_status_permalink":{"url":"https:\/\/t.co\/EQtVcczyyD","expanded":"https:\/\/twitter.com\/nanj16990709\/status\/1089174691703488512","display":"twitter.com\/nanj16990709\/s\u2026"},"is_quote_status":true,"quote_count":0,"reply_count":0,"retweet_count":0,"favorite_count":0,"entities":{"hashtags":[{"text":"share","indices":[48,54]},{"text":"JusticeForMahohon","indices":[55,73]},{"text":"JusticeForMaho","indices":[74,89]},{"text":"ngt48","indices":[90,96]},{"text":"ngt","indices":[97,101]},{"text":"inapooh0725","indices":[103,115]},{"text":"criminal","indices":[116,125]},{"text":"crime","indices":[126,132]},{"text":"cnn","indices":[133,137]}],"urls":[],"user_mentions":[{"screen_name":"johnkgalbraith","name":"\u30a2\u30c3\u30ad\u30fc (\u0411\u043e\u0440\u0438\u0441 \u041c\u0438\u0445\u0430\u0439\u043b\u043e\u0432\u0438\u0447 \u041a\u0443\u043b\u0438\u043a\u043e\u0432)","id":131222694,"id_str":"131222694","indices":[3,18]}],"symbols":[]},"favorited":false,"retweeted":false,"filter_level":"low","lang":"en","timestamp_ms":"1548571297213"}
{"created_at":"Sun Jan 27 06:41:40 +0000 2019","id":1089413109436043264,"id_str":"1089413109436043264","text":"@MaraReinstein with the advent of #metoo and this #leavingneverland doc, it's easy to see why these abuses are so p\u2026 https:\/\/t.co\/qud1H0XIYD","display_text_range":[15,140],"source":"\u003ca href=\"http:\/\/twitter.com\" rel=\"nofollow\"\u003eTwitter Web Client\u003c\/a\u003e","truncated":true,"in_reply_to_status_id":1089027041800777728,"in_reply_to_status_id_str":"1089027041800777728","in_reply_to_user_id":369838190,"in_reply_to_user_id_str":"369838190","in_reply_to_screen_name":"MaraReinstein","user":{"id":2596497720,"id_str":"2596497720","name":"counted for the cure","screen_name":"counted4thecure","location":null,"url":"http:\/\/facebook.com\/countedforthecure","description":"hope for a myeloma patient support foundation-because patients count","translator_type":"none","protected":false,"verified":false,"followers_count":34,"friends_count":99,"listed_count":1,"favourites_count":194,"statuses_count":195,"created_at":"Mon Jun 30 15:22:28 +0000 2014","utc_offset":null,"time_zone":null,"geo_enabled":false,"lang":"en","contributors_enabled":false,"is_translator":false,"profile_background_color":"000000","profile_background_image_url":"http:\/\/abs.twimg.com\/images\/themes\/theme1\/bg.png","profile_background_image_url_https":"https:\/\/abs.twimg.com\/images\/themes\/theme1\/bg.png","profile_background_tile":false,"profile_link_color":"ABB8C2","profile_sidebar_border_color":"000000","profile_sidebar_fill_color":"000000","profile_text_color":"000000","profile_use_background_image":false,"profile_image_url":"http:\/\/pbs.twimg.com\/profile_images\/932443491677982720\/5XjvJ9it_normal.jpg","profile_image_url_https":"https:\/\/pbs.twimg.com\/profile_images\/932443491677982720\/5XjvJ9it_normal.jpg","profile_banner_url":"https:\/\/pbs.twimg.com\/profile_banners\/2596497720\/1511145681","default_profile":false,"default_profile_image":false,"following":null,"follow_request_sent":null,"notifications":null},"geo":null,"coordinates":null,"place":null,"contributors":null,"is_quote_status":false,"extended_tweet":{"full_text":"@MaraReinstein with the advent of #metoo and this #leavingneverland doc, it's easy to see why these abuses are so prevalent.  it's society that's in part responsible for creating sexual abuse victims by refusing to believe even small children instead of their idols and those in power.","display_text_range":[15,285],"entities":{"hashtags":[{"text":"metoo","indices":[34,40]},{"text":"leavingneverland","indices":[50,67]}],"urls":[],"user_mentions":[{"screen_name":"MaraReinstein","name":"Mara Reinstein","id":369838190,"id_str":"369838190","indices":[0,14]}],"symbols":[]}},"quote_count":0,"reply_count":0,"retweet_count":0,"favorite_count":0,"entities":{"hashtags":[{"text":"metoo","indices":[34,40]},{"text":"leavingneverland","indices":[50,67]}],"urls":[{"url":"https:\/\/t.co\/qud1H0XIYD","expanded_url":"https:\/\/twitter.com\/i\/web\/status\/1089413109436043264","display_url":"twitter.com\/i\/web\/status\/1\u2026","indices":[117,140]}],"user_mentions":[{"screen_name":"MaraReinstein","name":"Mara Reinstein","id":369838190,"id_str":"369838190","indices":[0,14]}],"symbols":[]},"favorited":false,"retweeted":false,"filter_level":"low","lang":"en","timestamp_ms":"1548571300263"}
{"created_at":"Sun Jan 27 06:41:41 +0000 2019","id":1089413113789575168,"id_str":"1089413113789575168","text":"RT @nanj16990709: https:\/\/t.co\/znDT4p8gtJ\n\u65b0\u3057\u3044\u306e\u3053\u3061\u3089\u3067\u3059","source":"\u003ca href=\"http:\/\/twitter.com\/download\/iphone\" rel=\"nofollow\"\u003eTwitter for iPhone\u003c\/a\u003e","truncated":false,"in_reply_to_status_id":null,"in_reply_to_status_id_str":null,"in_reply_to_user_id":null,"in_reply_to_user_id_str":null,"in_reply_to_screen_name":null,"user":{"id":1082059677549047808,"id_str":"1082059677549047808","name":"\u5c71\u53e3\u771f\u5e06@NGT48\u3092\u52a9\u3051\u305f\u3044","screen_name":"yamaguchi_maho_","location":null,"url":null,"description":"#NGT48 #\u5c71\u53e3\u771f\u5e06 \u3055\u3093\u3092\u52a9\u3051\u305f\u3044\u3002\u7686\u3055\u3093\u306e\u3054\u5354\u529b\u304a\u9858\u3044\u81f4\u3057\u307e\u3059\ud83d\ude2d #justiceformahoh\u25cbn \u306f \u30a2\u30ab\u30a6\u30f3\u30c8\u30ed\u30c3\u25cb\u306b\u306a\u308b\u53ef\u80fd\u6027\u304c\u3042\u308a\u307e\u3059\u3002\u6c17\u3092\u3064\u3051\u3066\u3002@Maho_yamaguchi_ \u306f\u51cd\u7d50\u3055\u308c\u307e\u3057\u305f\u3002","translator_type":"none","protected":false,"verified":false,"followers_count":34,"friends_count":49,"listed_count":0,"favourites_count":1492,"statuses_count":893,"created_at":"Sun Jan 06 23:41:45 +0000 2019","utc_offset":null,"time_zone":null,"geo_enabled":false,"lang":"en","contributors_enabled":false,"is_translator":false,"profile_background_color":"F5F8FA","profile_background_image_url":"","profile_background_image_url_https":"","profile_background_tile":false,"profile_link_color":"1DA1F2","profile_sidebar_border_color":"C0DEED","profile_sidebar_fill_color":"DDEEF6","profile_text_color":"333333","profile_use_background_image":true,"profile_image_url":"http:\/\/pbs.twimg.com\/profile_images\/1086121252379492357\/GJWDEZjq_normal.jpg","profile_image_url_https":"https:\/\/pbs.twimg.com\/profile_images\/1086121252379492357\/GJWDEZjq_normal.jpg","profile_banner_url":"https:\/\/pbs.twimg.com\/profile_banners\/1082059677549047808\/1547786461","default_profile":true,"default_profile_image":false,"following":null,"follow_request_sent":null,"notifications":null},"geo":null,"coordinates":null,"place":null,"contributors":null,"retweeted_status":{"created_at":"Sat Jan 26 16:07:45 +0000 2019","id":1089193180107427840,"id_str":"1089193180107427840","text":"https:\/\/t.co\/znDT4p8gtJ\n\u65b0\u3057\u3044\u306e\u3053\u3061\u3089\u3067\u3059","source":"\u003ca href=\"http:\/\/twitter.com\/download\/android\" rel=\"nofollow\"\u003eTwitter for Android\u003c\/a\u003e","truncated":false,"in_reply_to_status_id":1087062415110332416,"in_reply_to_status_id_str":"1087062415110332416","in_reply_to_user_id":1086678143610441728,"in_reply_to_user_id_str":"1086678143610441728","in_reply_to_screen_name":"nanj16990709","user":{"id":1086678143610441728,"id_str":"1086678143610441728","name":"nanj","screen_name":"nanj16990709","location":null,"url":null,"description":"#JusticeForMahohon \u52dd\u624b\u306b\u30d5\u30a9\u30ed\u30fc\u3057\u307e\u3059 \u76ee\u969c\u308a\u306a\u3089\u30d6\u30ed\u30c3\u30af\u3057\u3066\u4e0b\u3055\u3044 \u3053\u306e\u4e8b\u4ef6\u304c\u89e3\u6c7a\u3059\u308c\u3070\u6d88\u3057\u307e\u3059\u3002","translator_type":"none","protected":false,"verified":false,"followers_count":257,"friends_count":462,"listed_count":2,"favourites_count":13,"statuses_count":32,"created_at":"Sat Jan 19 17:33:53 +0000 2019","utc_offset":null,"time_zone":null,"geo_enabled":false,"lang":"ja","contributors_enabled":false,"is_translator":false,"profile_background_color":"F5F8FA","profile_background_image_url":"","profile_background_image_url_https":"","profile_background_tile":false,"profile_link_color":"1DA1F2","profile_sidebar_border_color":"C0DEED","profile_sidebar_fill_color":"DDEEF6","profile_text_color":"333333","profile_use_background_image":true,"profile_image_url":"http:\/\/pbs.twimg.com\/profile_images\/1087777297099149312\/lUFLC5qD_normal.jpg","profile_image_url_https":"https:\/\/pbs.twimg.com\/profile_images\/1087777297099149312\/lUFLC5qD_normal.jpg","default_profile":true,"default_profile_image":false,"following":null,"follow_request_sent":null,"notifications":null},"geo":null,"coordinates":null,"place":null,"contributors":null,"quoted_status_id":1089174691703488512,"quoted_status_id_str":"1089174691703488512","quoted_status":{"created_at":"Sat Jan 26 14:54:17 +0000 2019","id":1089174691703488512,"id_str":"1089174691703488512","text":"Please read this article, and think about what\u2019s right, what justice is.\nHelp us reveal the whole truth by sharing\u2026 https:\/\/t.co\/g3Rx7znqxr","display_text_range":[0,140],"source":"\u003ca href=\"http:\/\/twitter.com\" rel=\"nofollow\"\u003eTwitter Web Client\u003c\/a\u003e","truncated":true,"in_reply_to_status_id":null,"in_reply_to_status_id_str":null,"in_reply_to_user_id":null,"in_reply_to_user_id_str":null,"in_reply_to_screen_name":null,"user":{"id":1086678143610441728,"id_str":"1086678143610441728","name":"nanj","screen_name":"nanj16990709","location":null,"url":null,"description":"#JusticeForMahohon \u52dd\u624b\u306b\u30d5\u30a9\u30ed\u30fc\u3057\u307e\u3059 \u76ee\u969c\u308a\u306a\u3089\u30d6\u30ed\u30c3\u30af\u3057\u3066\u4e0b\u3055\u3044 \u3053\u306e\u4e8b\u4ef6\u304c\u89e3\u6c7a\u3059\u308c\u3070\u6d88\u3057\u307e\u3059\u3002","translator_type":"none","protected":false,"verified":false,"followers_count":257,"friends_count":462,"listed_count":2,"favourites_count":13,"statuses_count":32,"created_at":"Sat Jan 19 17:33:53 +0000 2019","utc_offset":null,"time_zone":null,"geo_enabled":false,"lang":"ja","contributors_enabled":false,"is_translator":false,"profile_background_color":"F5F8FA","profile_background_image_url":"","profile_background_image_url_https":"","profile_background_tile":false,"profile_link_color":"1DA1F2","profile_sidebar_border_color":"C0DEED","profile_sidebar_fill_color":"DDEEF6","profile_text_color":"333333","profile_use_background_image":true,"profile_image_url":"http:\/\/pbs.twimg.com\/profile_images\/1087777297099149312\/lUFLC5qD_normal.jpg","profile_image_url_https":"https:\/\/pbs.twimg.com\/profile_images\/1087777297099149312\/lUFLC5qD_normal.jpg","default_profile":true,"default_profile_image":false,"following":null,"follow_request_sent":null,"notifications":null},"geo":null,"coordinates":null,"place":null,"contributors":null,"is_quote_status":false,"extended_tweet":{"full_text":"Please read this article, and think about what\u2019s right, what justice is.\nHelp us reveal the whole truth by sharing this story.\nWe NEED YOUR HELP.\n\n#PleaseHelp #JusticeForMahohon #share #sorrynotsorry #NeverForge #MeToo #YamaguchiMaho #\u5c71\u53e3\u771f\u5e06 https:\/\/t.co\/R6yXUZsV7M","display_text_range":[0,239],"entities":{"hashtags":[{"text":"PleaseHelp","indices":[147,158]},{"text":"JusticeForMahohon","indices":[159,177]},{"text":"share","indices":[178,184]},{"text":"sorrynotsorry","indices":[185,199]},{"text":"NeverForge","indices":[200,211]},{"text":"MeToo","indices":[212,218]},{"text":"YamaguchiMaho","indices":[219,233]},{"text":"\u5c71\u53e3\u771f\u5e06","indices":[234,239]}],"urls":[],"user_mentions":[],"symbols":[],"media":[{"id":1089174589890940928,"id_str":"1089174589890940928","indices":[240,263],"media_url":"http:\/\/pbs.twimg.com\/media\/Dx2GhNDU0AAoByc.jpg","media_url_https":"https:\/\/pbs.twimg.com\/media\/Dx2GhNDU0AAoByc.jpg","url":"https:\/\/t.co\/R6yXUZsV7M","display_url":"pic.twitter.com\/R6yXUZsV7M","expanded_url":"https:\/\/twitter.com\/nanj16990709\/status\/1089174691703488512\/photo\/1","type":"photo","sizes":{"thumb":{"w":150,"h":150,"resize":"crop"},"small":{"w":375,"h":680,"resize":"fit"},"large":{"w":1129,"h":2048,"resize":"fit"},"medium":{"w":662,"h":1200,"resize":"fit"}}},{"id":1089174614029217792,"id_str":"1089174614029217792","indices":[240,263],"media_url":"http:\/\/pbs.twimg.com\/media\/Dx2Gim-VsAA8YuU.jpg","media_url_https":"https:\/\/pbs.twimg.com\/media\/Dx2Gim-VsAA8YuU.jpg","url":"https:\/\/t.co\/R6yXUZsV7M","display_url":"pic.twitter.com\/R6yXUZsV7M","expanded_url":"https:\/\/twitter.com\/nanj16990709\/status\/1089174691703488512\/photo\/1","type":"photo","sizes":{"thumb":{"w":150,"h":150,"resize":"crop"},"medium":{"w":661,"h":1200,"resize":"fit"},"large":{"w":1128,"h":2048,"resize":"fit"},"small":{"w":375,"h":680,"resize":"fit"}}},{"id":1089174623302836225,"id_str":"1089174623302836225","indices":[240,263],"media_url":"http:\/\/pbs.twimg.com\/media\/Dx2GjJhV4AESKlN.jpg","media_url_https":"https:\/\/pbs.twimg.com\/media\/Dx2GjJhV4AESKlN.jpg","url":"https:\/\/t.co\/R6yXUZsV7M","display_url":"pic.twitter.com\/R6yXUZsV7M","expanded_url":"https:\/\/twitter.com\/nanj16990709\/status\/1089174691703488512\/photo\/1","type":"photo","sizes":{"thumb":{"w":150,"h":150,"resize":"crop"},"medium":{"w":660,"h":1200,"resize":"fit"},"small":{"w":374,"h":680,"resize":"fit"},"large":{"w":1127,"h":2048,"resize":"fit"}}},{"id":1089174638012157952,"id_str":"1089174638012157952","indices":[240,263],"media_url":"http:\/\/pbs.twimg.com\/media\/Dx2GkAUUUAAlQVM.jpg","media_url_https":"https:\/\/pbs.twimg.com\/media\/Dx2GkAUUUAAlQVM.jpg","url":"https:\/\/t.co\/R6yXUZsV7M","display_url":"pic.twitter.com\/R6yXUZsV7M","expanded_url":"https:\/\/twitter.com\/nanj16990709\/status\/1089174691703488512\/photo\/1","type":"photo","sizes":{"large":{"w":1164,"h":2048,"resize":"fit"},"thumb":{"w":150,"h":150,"resize":"crop"},"small":{"w":386,"h":680,"resize":"fit"},"medium":{"w":682,"h":1200,"resize":"fit"}}}]},"extended_entities":{"media":[{"id":1089174589890940928,"id_str":"1089174589890940928","indices":[240,263],"media_url":"http:\/\/pbs.twimg.com\/media\/Dx2GhNDU0AAoByc.jpg","media_url_https":"https:\/\/pbs.twimg.com\/media\/Dx2GhNDU0AAoByc.jpg","url":"https:\/\/t.co\/R6yXUZsV7M","display_url":"pic.twitter.com\/R6yXUZsV7M","expanded_url":"https:\/\/twitter.com\/nanj16990709\/status\/1089174691703488512\/photo\/1","type":"photo","sizes":{"thumb":{"w":150,"h":150,"resize":"crop"},"small":{"w":375,"h":680,"resize":"fit"},"large":{"w":1129,"h":2048,"resize":"fit"},"medium":{"w":662,"h":1200,"resize":"fit"}}},{"id":1089174614029217792,"id_str":"1089174614029217792","indices":[240,263],"media_url":"http:\/\/pbs.twimg.com\/media\/Dx2Gim-VsAA8YuU.jpg","media_url_https":"https:\/\/pbs.twimg.com\/media\/Dx2Gim-VsAA8YuU.jpg","url":"https:\/\/t.co\/R6yXUZsV7M","display_url":"pic.twitter.com\/R6yXUZsV7M","expanded_url":"https:\/\/twitter.com\/nanj16990709\/status\/1089174691703488512\/photo\/1","type":"photo","sizes":{"thumb":{"w":150,"h":150,"resize":"crop"},"medium":{"w":661,"h":1200,"resize":"fit"},"large":{"w":1128,"h":2048,"resize":"fit"},"small":{"w":375,"h":680,"resize":"fit"}}},{"id":1089174623302836225,"id_str":"1089174623302836225","indices":[240,263],"media_url":"http:\/\/pbs.twimg.com\/media\/Dx2GjJhV4AESKlN.jpg","media_url_https":"https:\/\/pbs.twimg.com\/media\/Dx2GjJhV4AESKlN.jpg","url":"https:\/\/t.co\/R6yXUZsV7M","display_url":"pic.twitter.com\/R6yXUZsV7M","expanded_url":"https:\/\/twitter.com\/nanj16990709\/status\/1089174691703488512\/photo\/1","type":"photo","sizes":{"thumb":{"w":150,"h":150,"resize":"crop"},"medium":{"w":660,"h":1200,"resize":"fit"},"small":{"w":374,"h":680,"resize":"fit"},"large":{"w":1127,"h":2048,"resize":"fit"}}},{"id":1089174638012157952,"id_str":"1089174638012157952","indices":[240,263],"media_url":"http:\/\/pbs.twimg.com\/media\/Dx2GkAUUUAAlQVM.jpg","media_url_https":"https:\/\/pbs.twimg.com\/media\/Dx2GkAUUUAAlQVM.jpg","url":"https:\/\/t.co\/R6yXUZsV7M","display_url":"pic.twitter.com\/R6yXUZsV7M","expanded_url":"https:\/\/twitter.com\/nanj16990709\/status\/1089174691703488512\/photo\/1","type":"photo","sizes":{"large":{"w":1164,"h":2048,"resize":"fit"},"thumb":{"w":150,"h":150,"resize":"crop"},"small":{"w":386,"h":680,"resize":"fit"},"medium":{"w":682,"h":1200,"resize":"fit"}}}]}},"quote_count":19,"reply_count":8,"retweet_count":357,"favorite_count":331,"entities":{"hashtags":[],"urls":[{"url":"https:\/\/t.co\/g3Rx7znqxr","expanded_url":"https:\/\/twitter.com\/i\/web\/status\/1089174691703488512","display_url":"twitter.com\/i\/web\/status\/1\u2026","indices":[116,139]}],"user_mentions":[],"symbols":[]},"favorited":false,"retweeted":false,"possibly_sensitive":false,"filter_level":"low","lang":"en"},"quoted_status_permalink":{"url":"https:\/\/t.co\/znDT4p8gtJ","expanded":"https:\/\/twitter.com\/nanj16990709\/status\/1089174691703488512?s=19","display":"twitter.com\/nanj16990709\/s\u2026"},"is_quote_status":true,"quote_count":0,"reply_count":0,"retweet_count":19,"favorite_count":25,"entities":{"hashtags":[],"urls":[{"url":"https:\/\/t.co\/znDT4p8gtJ","expanded_url":"https:\/\/twitter.com\/nanj16990709\/status\/1089174691703488512?s=19","display_url":"twitter.com\/nanj16990709\/s\u2026","indices":[0,23]}],"user_mentions":[],"symbols":[]},"favorited":false,"retweeted":false,"possibly_sensitive":false,"filter_level":"low","lang":"ja"},"quoted_status_id":1089174691703488512,"quoted_status_id_str":"1089174691703488512","quoted_status":{"created_at":"Sat Jan 26 14:54:17 +0000 2019","id":1089174691703488512,"id_str":"1089174691703488512","text":"Please read this article, and think about what\u2019s right, what justice is.\nHelp us reveal the whole truth by sharing\u2026 https:\/\/t.co\/g3Rx7znqxr","display_text_range":[0,140],"source":"\u003ca href=\"http:\/\/twitter.com\" rel=\"nofollow\"\u003eTwitter Web Client\u003c\/a\u003e","truncated":true,"in_reply_to_status_id":null,"in_reply_to_status_id_str":null,"in_reply_to_user_id":null,"in_reply_to_user_id_str":null,"in_reply_to_screen_name":null,"user":{"id":1086678143610441728,"id_str":"1086678143610441728","name":"nanj","screen_name":"nanj16990709","location":null,"url":null,"description":"#JusticeForMahohon \u52dd\u624b\u306b\u30d5\u30a9\u30ed\u30fc\u3057\u307e\u3059 \u76ee\u969c\u308a\u306a\u3089\u30d6\u30ed\u30c3\u30af\u3057\u3066\u4e0b\u3055\u3044 \u3053\u306e\u4e8b\u4ef6\u304c\u89e3\u6c7a\u3059\u308c\u3070\u6d88\u3057\u307e\u3059\u3002","translator_type":"none","protected":false,"verified":false,"followers_count":257,"friends_count":462,"listed_count":2,"favourites_count":13,"statuses_count":32,"created_at":"Sat Jan 19 17:33:53 +0000 2019","utc_offset":null,"time_zone":null,"geo_enabled":false,"lang":"ja","contributors_enabled":false,"is_translator":false,"profile_background_color":"F5F8FA","profile_background_image_url":"","profile_background_image_url_https":"","profile_background_tile":false,"profile_link_color":"1DA1F2","profile_sidebar_border_color":"C0DEED","profile_sidebar_fill_color":"DDEEF6","profile_text_color":"333333","profile_use_background_image":true,"profile_image_url":"http:\/\/pbs.twimg.com\/profile_images\/1087777297099149312\/lUFLC5qD_normal.jpg","profile_image_url_https":"https:\/\/pbs.twimg.com\/profile_images\/1087777297099149312\/lUFLC5qD_normal.jpg","default_profile":true,"default_profile_image":false,"following":null,"follow_request_sent":null,"notifications":null},"geo":null,"coordinates":null,"place":null,"contributors":null,"is_quote_status":false,"extended_tweet":{"full_text":"Please read this article, and think about what\u2019s right, what justice is.\nHelp us reveal the whole truth by sharing this story.\nWe NEED YOUR HELP.\n\n#PleaseHelp #JusticeForMahohon #share #sorrynotsorry #NeverForge #MeToo #YamaguchiMaho #\u5c71\u53e3\u771f\u5e06 https:\/\/t.co\/R6yXUZsV7M","display_text_range":[0,239],"entities":{"hashtags":[{"text":"PleaseHelp","indices":[147,158]},{"text":"JusticeForMahohon","indices":[159,177]},{"text":"share","indices":[178,184]},{"text":"sorrynotsorry","indices":[185,199]},{"text":"NeverForge","indices":[200,211]},{"text":"MeToo","indices":[212,218]},{"text":"YamaguchiMaho","indices":[219,233]},{"text":"\u5c71\u53e3\u771f\u5e06","indices":[234,239]}],"urls":[],"user_mentions":[],"symbols":[],"media":[{"id":1089174589890940928,"id_str":"1089174589890940928","indices":[240,263],"media_url":"http:\/\/pbs.twimg.com\/media\/Dx2GhNDU0AAoByc.jpg","media_url_https":"https:\/\/pbs.twimg.com\/media\/Dx2GhNDU0AAoByc.jpg","url":"https:\/\/t.co\/R6yXUZsV7M","display_url":"pic.twitter.com\/R6yXUZsV7M","expanded_url":"https:\/\/twitter.com\/nanj16990709\/status\/1089174691703488512\/photo\/1","type":"photo","sizes":{"thumb":{"w":150,"h":150,"resize":"crop"},"small":{"w":375,"h":680,"resize":"fit"},"large":{"w":1129,"h":2048,"resize":"fit"},"medium":{"w":662,"h":1200,"resize":"fit"}}},{"id":1089174614029217792,"id_str":"1089174614029217792","indices":[240,263],"media_url":"http:\/\/pbs.twimg.com\/media\/Dx2Gim-VsAA8YuU.jpg","media_url_https":"https:\/\/pbs.twimg.com\/media\/Dx2Gim-VsAA8YuU.jpg","url":"https:\/\/t.co\/R6yXUZsV7M","display_url":"pic.twitter.com\/R6yXUZsV7M","expanded_url":"https:\/\/twitter.com\/nanj16990709\/status\/1089174691703488512\/photo\/1","type":"photo","sizes":{"thumb":{"w":150,"h":150,"resize":"crop"},"medium":{"w":661,"h":1200,"resize":"fit"},"large":{"w":1128,"h":2048,"resize":"fit"},"small":{"w":375,"h":680,"resize":"fit"}}},{"id":1089174623302836225,"id_str":"1089174623302836225","indices":[240,263],"media_url":"http:\/\/pbs.twimg.com\/media\/Dx2GjJhV4AESKlN.jpg","media_url_https":"https:\/\/pbs.twimg.com\/media\/Dx2GjJhV4AESKlN.jpg","url":"https:\/\/t.co\/R6yXUZsV7M","display_url":"pic.twitter.com\/R6yXUZsV7M","expanded_url":"https:\/\/twitter.com\/nanj16990709\/status\/1089174691703488512\/photo\/1","type":"photo","sizes":{"thumb":{"w":150,"h":150,"resize":"crop"},"medium":{"w":660,"h":1200,"resize":"fit"},"small":{"w":374,"h":680,"resize":"fit"},"large":{"w":1127,"h":2048,"resize":"fit"}}},{"id":1089174638012157952,"id_str":"1089174638012157952","indices":[240,263],"media_url":"http:\/\/pbs.twimg.com\/media\/Dx2GkAUUUAAlQVM.jpg","media_url_https":"https:\/\/pbs.twimg.com\/media\/Dx2GkAUUUAAlQVM.jpg","url":"https:\/\/t.co\/R6yXUZsV7M","display_url":"pic.twitter.com\/R6yXUZsV7M","expanded_url":"https:\/\/twitter.com\/nanj16990709\/status\/1089174691703488512\/photo\/1","type":"photo","sizes":{"large":{"w":1164,"h":2048,"resize":"fit"},"thumb":{"w":150,"h":150,"resize":"crop"},"small":{"w":386,"h":680,"resize":"fit"},"medium":{"w":682,"h":1200,"resize":"fit"}}}]},"extended_entities":{"media":[{"id":1089174589890940928,"id_str":"1089174589890940928","indices":[240,263],"media_url":"http:\/\/pbs.twimg.com\/media\/Dx2GhNDU0AAoByc.jpg","media_url_https":"https:\/\/pbs.twimg.com\/media\/Dx2GhNDU0AAoByc.jpg","url":"https:\/\/t.co\/R6yXUZsV7M","display_url":"pic.twitter.com\/R6yXUZsV7M","expanded_url":"https:\/\/twitter.com\/nanj16990709\/status\/1089174691703488512\/photo\/1","type":"photo","sizes":{"thumb":{"w":150,"h":150,"resize":"crop"},"small":{"w":375,"h":680,"resize":"fit"},"large":{"w":1129,"h":2048,"resize":"fit"},"medium":{"w":662,"h":1200,"resize":"fit"}}},{"id":1089174614029217792,"id_str":"1089174614029217792","indices":[240,263],"media_url":"http:\/\/pbs.twimg.com\/media\/Dx2Gim-VsAA8YuU.jpg","media_url_https":"https:\/\/pbs.twimg.com\/media\/Dx2Gim-VsAA8YuU.jpg","url":"https:\/\/t.co\/R6yXUZsV7M","display_url":"pic.twitter.com\/R6yXUZsV7M","expanded_url":"https:\/\/twitter.com\/nanj16990709\/status\/1089174691703488512\/photo\/1","type":"photo","sizes":{"thumb":{"w":150,"h":150,"resize":"crop"},"medium":{"w":661,"h":1200,"resize":"fit"},"large":{"w":1128,"h":2048,"resize":"fit"},"small":{"w":375,"h":680,"resize":"fit"}}},{"id":1089174623302836225,"id_str":"1089174623302836225","indices":[240,263],"media_url":"http:\/\/pbs.twimg.com\/media\/Dx2GjJhV4AESKlN.jpg","media_url_https":"https:\/\/pbs.twimg.com\/media\/Dx2GjJhV4AESKlN.jpg","url":"https:\/\/t.co\/R6yXUZsV7M","display_url":"pic.twitter.com\/R6yXUZsV7M","expanded_url":"https:\/\/twitter.com\/nanj16990709\/status\/1089174691703488512\/photo\/1","type":"photo","sizes":{"thumb":{"w":150,"h":150,"resize":"crop"},"medium":{"w":660,"h":1200,"resize":"fit"},"small":{"w":374,"h":680,"resize":"fit"},"large":{"w":1127,"h":2048,"resize":"fit"}}},{"id":1089174638012157952,"id_str":"1089174638012157952","indices":[240,263],"media_url":"http:\/\/pbs.twimg.com\/media\/Dx2GkAUUUAAlQVM.jpg","media_url_https":"https:\/\/pbs.twimg.com\/media\/Dx2GkAUUUAAlQVM.jpg","url":"https:\/\/t.co\/R6yXUZsV7M","display_url":"pic.twitter.com\/R6yXUZsV7M","expanded_url":"https:\/\/twitter.com\/nanj16990709\/status\/1089174691703488512\/photo\/1","type":"photo","sizes":{"large":{"w":1164,"h":2048,"resize":"fit"},"thumb":{"w":150,"h":150,"resize":"crop"},"small":{"w":386,"h":680,"resize":"fit"},"medium":{"w":682,"h":1200,"resize":"fit"}}}]}},"quote_count":19,"reply_count":8,"retweet_count":357,"favorite_count":331,"entities":{"hashtags":[],"urls":[{"url":"https:\/\/t.co\/g3Rx7znqxr","expanded_url":"https:\/\/twitter.com\/i\/web\/status\/1089174691703488512","display_url":"twitter.com\/i\/web\/status\/1\u2026","indices":[116,139]}],"user_mentions":[],"symbols":[]},"favorited":false,"retweeted":false,"possibly_sensitive":false,"filter_level":"low","lang":"en"},"quoted_status_permalink":{"url":"https:\/\/t.co\/znDT4p8gtJ","expanded":"https:\/\/twitter.com\/nanj16990709\/status\/1089174691703488512?s=19","display":"twitter.com\/nanj16990709\/s\u2026"},"is_quote_status":true,"quote_count":0,"reply_count":0,"retweet_count":0,"favorite_count":0,"entities":{"hashtags":[],"urls":[{"url":"https:\/\/t.co\/znDT4p8gtJ","expanded_url":"https:\/\/twitter.com\/nanj16990709\/status\/1089174691703488512?s=19","display_url":"twitter.com\/nanj16990709\/s\u2026","indices":[18,41]}],"user_mentions":[{"screen_name":"nanj16990709","name":"nanj","id":1086678143610441728,"id_str":"1086678143610441728","indices":[3,16]}],"symbols":[]},"favorited":false,"retweeted":false,"possibly_sensitive":false,"filter_level":"low","lang":"ja","timestamp_ms":"1548571301301"}
